django_core_api/__init__.py
django_core_api/admin.py
django_core_api/apps.py
django_core_api/cache.py
django_core_api/celery.py
django_core_api/exceptions.py
django_core_api/filters.py
django_core_api/logging_filters.py
django_core_api/managers.py
django_core_api/middleware.py
django_core_api/models.py
django_core_api/routers.py
django_core_api/serializers.py
django_core_api/settings.py
django_core_api/signals.py
django_core_api/storage.py
django_core_api/tasks.py
django_core_api/tests.py
django_core_api/urls.py
django_core_api/views/__init__.py
django_core_api/views/healthcheck_views.py
django_core_api/views/nested_viewsets.py
django_core_api/views/single_nested_viewsets.py
django_core_api/views/stats_views.py
django_core_api/views/viewsets.py
django_core_api-0.1.0rc6.dist-info/LICENSE.md
django_core_api-0.1.0rc6.dist-info/WHEEL
django_core_api-0.1.0rc6.dist-info/METADATA
django_core_api-0.1.0rc6.dist-info/RECORD
