Metadata-Version: 2.1
Name: django-core-api
Version: 0.1.0rc6
Summary: 
Author: João Daher
Author-email: joao@daher.dev
Requires-Python: >=3.8,<4.0
Classifier: Programming Language :: Python :: 3
Classifier: Programming Language :: Python :: 3.8
Requires-Dist: Django (>=3,<4)
Requires-Dist: celery
Requires-Dist: dj-database-url (>=0,<1)
Requires-Dist: django-autoslug-iplweb (>=1,<2)
Requires-Dist: django-filter (>=2,<3)
Requires-Dist: django-model-utils (>=4,<5)
Requires-Dist: django-ordered-model (>=3,<4)
Requires-Dist: django-redis (>=4,<5)
Requires-Dist: django-storages (>=1,<2)
Requires-Dist: djangorestframework (>=3,<4)
Requires-Dist: drf-extensions (>=0,<1)
Requires-Dist: envparse (>=0,<1)
Requires-Dist: psycopg2-binary (>=2,<3)
Requires-Dist: python-dateutil
Requires-Dist: whitenoise (>=5,<6)
